uniconnect/__init__.py
uniconnect/auth.py
uniconnect/client.py
uniconnect/constants.py
uniconnect/dbapi.py
uniconnect/exceptions.py
uniconnect/logging.py
uniconnect/redirect.py
uniconnect/transaction.py
uniconnect_python_client-0.7.0.dist-info/LICENSE
uniconnect_python_client-0.7.0.dist-info/METADATA
uniconnect_python_client-0.7.0.dist-info/WHEEL
uniconnect_python_client-0.7.0.dist-info/top_level.txt
uniconnect_python_client-0.7.0.dist-info/RECORD
